Topsis_Arnav_101917097/101917097.py
Topsis_Arnav_101917097/__init__.py
Topsis_Arnav_101917097-0.0.1.dist-info/LICENSE
Topsis_Arnav_101917097-0.0.1.dist-info/METADATA
Topsis_Arnav_101917097-0.0.1.dist-info/WHEEL
Topsis_Arnav_101917097-0.0.1.dist-info/entry_points.txt
Topsis_Arnav_101917097-0.0.1.dist-info/top_level.txt
Topsis_Arnav_101917097-0.0.1.dist-info/RECORD
