Metadata-Version: 2.1
Name: Topsis-Arnav-101917097
Version: 0.0.1
Summary: Multi-Criteria Decision Making
Author: Arnav Agarwal
Author-email: aagarwal6_be19@thapar.edu
License: MIT
Keywords: python,best model,Topsis,multi-criteria decision making,assignment
Platform: UNKNOWN
Classifier: Programming Language :: Python :: 3
Classifier: License :: OSI Approved :: MIT License
Classifier: Operating System :: OS Independent
License-File: LICENSE
Requires-Dist: pandas
